{
  "client1": 
    {
  "ClientIdentifierId": "12345678",
  "IdType": "NationalId",
  "IdNumber": "941467567v",
  "DateOfBirth": "23/03/1441",
  "Age": 20,
  "PlaceOfBirth": "Colombo",
  "FirstNameEn": "Shehan",
  "SecondNameEn": "Chamara",
  "ThirdNameEn": "",
  "LastNameEn": "Cooray",
  "HealthId": "1234",
  "FirstNameAr": "محمد علي",
  "SecondNameAr": "محمد علي",
  "ThirdNameAr": "محمد علي",
  "LastNameAr": "محمد علي",
  "Gender": "M",
  "Nationality": "SriLankan",
  "NationalityCode": "LK",
  "Occupation": "IOT-Engineer",
  "MaritalStatus": "Single",
  "MaritalStatusCode": "S",
  "PatientStatus": "Alive"
},
   "client2":     {
  "ClientIdentifierId": "12345677",
  "IdType": "NationalId",
  "IdNumber": "941467547v",
  "DateOfBirth": "23/03/2001",
  "Age": 20,
  "PlaceOfBirth": "Colombo",
  "FirstNameEn": "Shehan",
  "SecondNameEn": "Chamara",
  "ThirdNameEn": "",
  "LastNameEn": "Cooray",
  "HealthId": "1234",
  "FirstNameAr": "محمد علي",
  "SecondNameAr": "محمد علي",
  "ThirdNameAr": "محمد علي",
  "LastNameAr": "محمد علي",
  "Gender": "M",
  "Nationality": "SriLankan",
  "NationalityCode": "LK",
  "Occupation": "IOT-Engineer",
  "MaritalStatus": "Single",
  "MaritalStatusCode": "S",
  "PatientStatus": "Alive"
},
  "bundle1": { "success": true, "outcome": { "id": "37f278b6-5697-11e9-8647-d663bd873d93", "total": "2", "entry": [ { "id": "12121212", "appointmentType": { "code": "ROUTINE" }, "status": "free", "start": "2018-05-13T00:00:00Z", "end": "2018-05-13T00:00:00Z" }, { "id": "23232323", "appointmentType": { "code": "ROUTINE" }, "status": "free", "start": "2018-05-13T00:00:00Z", "end": "2018-05-13T00:00:00Z" } ] } }
  
}
